{
    "/css/admin-all-ltr.css": "/css/admin-all-ltr.css?id=d6b38e59d6a72a493fe5",
    "/css/admin-all-rtl.css": "/css/admin-all-rtl.css?id=987c49720c465b63f173",
    "/js/admin-all-ltr.js": "/js/admin-all-ltr.js?id=c4c58b51122abccf2fd9",
    "/js/admin-all-rtl.js": "/js/admin-all-rtl.js?id=47c879eb427051b12226",
    "/css/theme-a.css": "/css/theme-a.css?id=871073980afa89793c57",
    "/css/theme-b.css": "/css/theme-b.css?id=574971e858e2b99e2cfb",
    "/css/theme-c.css": "/css/theme-c.css?id=b988a92b914631e702dd",
    "/css/theme-d.css": "/css/theme-d.css?id=96f1837fc344f3ebb165",
    "/css/theme-e.css": "/css/theme-e.css?id=dba5aee9077e96629d00",
    "/css/theme-f.css": "/css/theme-f.css?id=aaea5d8f80a97a8bc8d9",
    "/css/theme-g.css": "/css/theme-g.css?id=03e0d2fac1f1f432c530",
    "/css/theme-h.css": "/css/theme-h.css?id=c6b1de5d85a1c47f4703",
    "/images/marker_red.png": "/images/marker_red.png?id=df302999c8f1e7c86fdc",
    "/img/mb-sample.jpg": "/img/mb-sample.jpg?id=eef807dce5b5f0186963",
    "/css/admin-membership-ltr.css": "/css/admin-membership-ltr.css?id=2a3d7ea9887fff5c33cb",
    "/css/admin-membership-rtl.css": "/css/admin-membership-rtl.css?id=bd50577991b8b6f7a85b",
    "/js/admin-membership-ltr.js": "/js/admin-membership-ltr.js?id=e9578897efcf33bb4a87",
    "/js/admin-membership-rtl.js": "/js/admin-membership-rtl.js?id=685f0c5825164ff86150",
    "/css/theme-ltr.css": "/css/theme-ltr.css?id=38cbc2655ce3f5cb03f9",
    "/js/revolution-slider/css/revolution-slider.css": "/js/revolution-slider/css/revolution-slider.css?id=14f53cd9290a596be7f3",
    "/js/revolution-slider/js/revolution-slider.js": "/js/revolution-slider/js/revolution-slider.js?id=2247680fdb15c8e5f95f",
    "/js/revolution-slider/js/extensions/revolution-slider-extensions.js": "/js/revolution-slider/js/extensions/revolution-slider-extensions.js?id=398c52965193ec6b29fa",
    "/js/ie.js": "/js/ie.js?id=0657ad4a514ac01a9094",
    "/js/main.js": "/js/main.js?id=8b627e552929e57b9a7c",
    "/admin-custom.css": "/admin-custom.css?id=76aaed6070002ff12cff",
    "/admin-custom.js": "/admin-custom.js?id=0d32060796aaa64216cb"
}
